aiocycletls/__init__.py
aiocycletls/client.py
aiocycletls/proxy.py
aiocycletls/browsers/__init__.py
aiocycletls/browsers/browser_base.py
aiocycletls/browsers/chrome.py
aiocycletls/enums/__init__.py
aiocycletls/enums/browser_type.py
aiocycletls/enums/extension_type.py
aiocycletls/enums/platform_type.py
aiocycletls/enums/system_platform.py
aiocycletls/models/__init__.py
aiocycletls/models/request.py
aiocycletls/models/response.py
aiocycletls/models/browser/__init__.py
aiocycletls/models/browser/browser_data.py
aiocycletls/models/browser/extension.py
aiocycletls/models/browser/platform_information.py
aiocycletls/models/browser/system_information.py
aiocycletls/models/browser/user_agent.py
aiocycletls-1.0.4.dist-info/METADATA
aiocycletls-1.0.4.dist-info/WHEEL
aiocycletls-1.0.4.dist-info/top_level.txt
aiocycletls-1.0.4.dist-info/RECORD
