Metadata-Version: 2.1
Name: aiocycletls
Version: 1.0.4
Summary: A python package for spoofing TLS
Home-page: https://github.com/HateMe02/async_cycletls_python
Author: HateMe02
License: none
Platform: UNKNOWN
